sinetstream/cmd/producer.py
sinetstream_cmd-1.7.0.dist-info/METADATA
sinetstream_cmd-1.7.0.dist-info/WHEEL
sinetstream_cmd-1.7.0.dist-info/top_level.txt
sinetstream_cmd-1.7.0.dist-info/RECORD
